<?xml version="1.0" encoding="UTF-8"?>
<song xmlns="http://openlyrics.info/namespace/2009/song" version="0.9">
  <properties>
    <titles>
      <title>Solemnes resuenen</title>
    </titles>
    <authors>
      <author>Desconocido</author>
    </authors>
    <songbooks>
      <songbook name="Tuya es la gloria 2022" entry="28"/>
    </songbooks>
    <publisher>Editorial Siembra</publisher>
    <themes>
      <theme>Adoración y Alabanza</theme>
      <theme>Esperanza y Segunda Venida</theme>
      <theme>Vida de Cristo</theme>
    </themes>
    <keywords>
      <keyword>Rey</keyword>
      <keyword>Salvador</keyword>
      <keyword>Amor</keyword>
      <keyword>Cruz</keyword>
      <keyword>Gloria</keyword>
    </keywords>
  </properties>
  <lyrics>
    <verse name="v1">
      <lines>Solemnes resuenen las voces de amor<br/>con gran regocijo tributen loor<br/>al Rey Soberano, el Buen Salvador;<br/>dignísimo es él del más alto honor.<br/></lines>
    </verse>
    <verse name="c">
      <lines>Alabad, alabad, alabad al gran Rey;<br/>adorad, adorad, adoradle su grey.<br/>Es nuestro escudo, baluarte y sostén,<br/>El Omnipotente por siglos. Amén.<br/></lines>
    </verse>
    <verse name="v2">
      <lines>Su amor infinito, ¿qué lengua dirá?<br/>Y ¿quién sus bondades jamás sondeará?<br/>Su misericordia no puede faltar,<br/>mil himnos alaben su nombre sin par.<br/></lines>
    </verse>
    <verse name="v3">
      <lines>Inmensa la obra de Cristo en la cruz,<br/>enorme la culpa se ve por su luz.<br/>Al mundo él vino, nos iluminó,<br/>y por nuestras culpas el justo murió.<br/></lines>
    </verse>
    <verse name="v4">
      <lines>Velad, fieles todos, velad con fervor,<br/>que viene muy pronto Jesús el Señor.<br/>Con notas alegres vendrá a reinar;<br/>a su eterna gloria os ha de llevar.<br/></lines>
    </verse>
  </lyrics>
</song>