<?xml version="1.0" encoding="UTF-8"?>
<song xmlns="http://openlyrics.info/namespace/2009/song" version="0.9">
  <properties>
    <titles>
      <title>Yo tengo un amigo que me ama</title>
    </titles>
    <authors>
      <author>Desconocido</author>
    </authors>
    <publisher>Editorial Siembra</publisher>
    <songbooks>
      <songbook name="Tuya es la Gloria 2022" entry="372"/>
    </songbooks>
    <themes>
      <theme>Adoración y Alabanza</theme>
      <theme>Iglesia y Comunidad</theme>
      <theme>Oración y Devoción Personal</theme>
    </themes>
    <keywords>
      <keyword>Amigo</keyword>
      <keyword>Jesús</keyword>
      <keyword>Amor</keyword>
      <keyword>Amistad</keyword>
      <keyword>Tierno</keyword>
    </keywords>
  </properties>
  <lyrics>
    <verse name="v1">
      <lines>Yo tengo un amigo que me ama,<br/>me ama, me ama.<br/>Yo tengo un amigo que me ama,<br/>su nombre es Jesús.<br/></lines>
    </verse>
    <verse name="c">
      <lines>/Él me ama, él me ama,<br/>él me ama con su tierno amor./<br/></lines>
    </verse>
    <verse name="v2">
      <lines>Tú tienes un amigo que te ama,<br/>te ama, te ama.<br/>Tú tienes un amigo que te ama,<br/>su nombre es Jesús.<br/></lines>
    </verse>
    <verse name="v3">
      <lines>Tenemos un amigo que nos ama,<br/>nos ama, nos ama.<br/>Tenemos un amigo que nos ama,<br/>su nombre es Jesús.<br/></lines>
    </verse>
  </lyrics>
</song>