<?xml version="1.0" encoding="UTF-8"?><song xmlns="http://openlyrics.info/namespace/2009/song" version="0.9"><properties><titles><title>244 TE NECESITO YA</title></titles><authors><author>Tuya es la Gloria D.R.</author></authors></properties><lyrics><verse name="v1"><lines>LA<br/>Te necesito ya, bendito Salvador;<br/>me infunde dulce paz tu tierna voz de amor.<br/></lines></verse><verse name="v2"><lines>Coro<br/>Te necesito, Cristo; sí, te necesito<br/>con corazón contrito acudo a ti.<br/></lines></verse><verse name="v3"><lines>Te necesito ya, mi Redentor serás;<br/>yo siempre venceré si Tú conmigo estás.<br/></lines></verse><verse name="v4"><lines>Te necesito ya, santísimo Señor;<br/>tuyo hazme, nada más, bendito Salvador.<br/></lines></verse></lyrics></song>